sam4u/__init__.py
sam4u/courses.py
sam4u/utils.py
sam4u-0.2.0.dist-info/METADATA
sam4u-0.2.0.dist-info/WHEEL
sam4u-0.2.0.dist-info/top_level.txt
sam4u-0.2.0.dist-info/RECORD
